setup.cfg
setup.py
lcat/__init__.py
lcat/util.py
lcat.egg-info/PKG-INFO
lcat.egg-info/SOURCES.txt
lcat.egg-info/dependency_links.txt
lcat.egg-info/requires.txt
lcat.egg-info/top_level.txt
lcat/analysis/__init__.py
lcat/analysis/tracheal_distance.py
lcat/loading/__init__.py
lcat/loading/annotations.py
lcat/loading/images.py
lcat/loading/scans.py
lcat/segmentation/__init__.py
lcat/segmentation/body.py
lcat/segmentation/lungs.py
scripts/lcat-featurize.py
scripts/lcat-visualize.py