Metadata-Version: 1.1
Name: lcat
Version: 0.1.6
Summary: Lung Cancer Action Team (LCAT) toolkit
Home-page: https://github.com/connorbrinton/lcat
Author: LCAT Team
Author-email: brinton@cs.stanford.edu
License: GPL-3.0
Download-URL: https://github.com/connorbrinton/lcat/archive/0.1.0.tar.gz
Keywords: CT,lung,biopsy
Platform: UNKNOWN
